UserIdentificationSystem/__init__.py
user_Identification_System-0.0.91.dist-info/LICENCE
user_Identification_System-0.0.91.dist-info/METADATA
user_Identification_System-0.0.91.dist-info/WHEEL
user_Identification_System-0.0.91.dist-info/top_level.txt
user_Identification_System-0.0.91.dist-info/RECORD
