Metadata-Version: 2.1
Name: user-Identification-System
Version: 0.0.91
Summary: A tool to help you build a signup and login system
Home-page: https://github.com/Ayaan-Imran/User-Indentifier-System
Author: Ayaan Imran
Author-email: miskiacuberayaan2509@gmail.com
Classifier: Programming Language :: Python :: 3
Classifier: License :: OSI Approved :: MIT License
Classifier: Operating System :: OS Independent
Requires-Python: >=3.6
License-File: LICENCE
